MethylVerseDash/.DS_Store
MethylVerseDash/__init__.py
MethylVerseDash/__main__.py
MethylVerseDash/commandline/__init__.py
MethylVerseDash/commandline/commands.py
MethylVerseDash/core/.DS_Store
MethylVerseDash/core/methyl_core.py
MethylVerseDash/core/microarray/.DS_Store
MethylVerseDash/core/microarray/RawArray.py
MethylVerseDash/core/microarray/__init__.py
MethylVerseDash/core/microarray/illumina_normalize.py
MethylVerseDash/core/microarray/read_IDAT.py
MethylVerseDash/core/microarray/read_illumina.c
MethylVerseDash/core/microarray/read_illumina.cpython-311-darwin.so
MethylVerseDash/core/microarray/read_illumina.pyx
MethylVerseDash/core/sequencing/.DS_Store
MethylVerseDash/core/sequencing/__init__.py
MethylVerseDash/core/sequencing/read_methyldackel/.DS_Store
MethylVerseDash/core/sequencing/read_methyldackel/__init__.py
MethylVerseDash/core/sequencing/read_methyldackel/kseq.h
MethylVerseDash/core/sequencing/read_methyldackel/process_methyldackel.c
MethylVerseDash/core/sequencing/read_methyldackel/process_methyldackel.h
MethylVerseDash/core/sequencing/read_methyldackel/read_methyldackel.c
MethylVerseDash/core/sequencing/read_methyldackel/read_methyldackel.cpython-311-darwin.so
MethylVerseDash/core/sequencing/read_methyldackel/read_methyldackel.pxd
MethylVerseDash/core/sequencing/read_methyldackel/read_methyldackel.pyx
MethylVerseDash/core/sequencing/seq_utilities.py
MethylVerseDash/core/sequencing/sequencing_core.py
MethylVerseDash/core/utilities.py
MethylVerseDash/data/.DS_Store
MethylVerseDash/data/__init__.py
MethylVerseDash/data/download_data.py
MethylVerseDash/data/import_data.py
MethylVerseDash/plot/__init__.py
MethylVerseDash/plot/plot_bokeh.py
MethylVerseDash/plot/plot_plt.py
MethylVerseDash/recipes/__init__.py
MethylVerseDash/recipes/recipes.py
MethylVerseDash/tools/.DS_Store
MethylVerseDash/tools/__init__.py
MethylVerseDash/tools/classifiers/.DS_Store
MethylVerseDash/tools/classifiers/Architectures/MultiClassEnsemble.py
methylversedash-1.1.1.dist-info/LICENSE.md
methylversedash-1.1.1.dist-info/METADATA
methylversedash-1.1.1.dist-info/WHEEL
methylversedash-1.1.1.dist-info/RECORD
